yaqd_adafruit/VERSION
yaqd_adafruit/__init__.py
yaqd_adafruit/__version__.py
yaqd_adafruit/_adafruit_stepper_motor_hat.py
yaqd_adafruit/adafruit-stepper-motor-hat.avpr
yaqd_adafruit/adafruit-stepper-motor-hat.toml
yaqd_adafruit-2023.6.0.dist-info/entry_points.txt
yaqd_adafruit-2023.6.0.dist-info/LICENSE
yaqd_adafruit-2023.6.0.dist-info/WHEEL
yaqd_adafruit-2023.6.0.dist-info/METADATA
yaqd_adafruit-2023.6.0.dist-info/RECORD
