Metadata-Version: 2.1
Name: yaqd-adafruit
Version: 2023.6.0
Summary: yaq daemons for Adafruit products
Home-page: https://yaq.fyi
Author: yaq developers
Requires-Python: >=3.7
Classifier: Development Status :: 2 - Pre-Alpha
Classifier: Intended Audience :: Science/Research
Classifier: License :: OSI Approved :: GNU Lesser General Public License v3 (LGPLv3)
Classifier: Natural Language :: English
Classifier: Programming Language :: Python :: 3
Classifier: Programming Language :: Python :: 3.7
Classifier: Programming Language :: Python :: 3.8
Classifier: Topic :: Scientific/Engineering
Requires-Dist: yaqd-core>=2021.12.0
Requires-Dist: adafruit-circuitpython-motorkit
Requires-Dist: adafruit-circuitpython-motor
Requires-Dist: gpiozero
Requires-Dist: black ; extra == "dev"
Requires-Dist: pre-commit ; extra == "dev"
Project-URL: Issues, https://github.com/yaq-project/yaqd-adafruit/issues
Project-URL: Source, https://github.com/yaq-project/yaqd-adafruit
Provides-Extra: dev
